helloworld.cp311-win32.pyd
hello_world_xprees1-0.0.0rc1.dev0.dist-info/METADATA
hello_world_xprees1-0.0.0rc1.dev0.dist-info/WHEEL
hello_world_xprees1-0.0.0rc1.dev0.dist-info/top_level.txt
hello_world_xprees1-0.0.0rc1.dev0.dist-info/RECORD
