Metadata-Version: 2.4
Name: hello_world_xprees1
Version: 0.0.0rc1.dev0
Summary: Python C extension example
Author: xprees1
Requires-Python: >=3.9
Dynamic: author
Dynamic: requires-python
